sl/__init__.py
sl/__main__.py
sl/handlers.py
sl/headers.py
sl/server.py
sl/util.py
sl/validate.py
ServeLight-3.4.4.dist-info/LICENSE.txt
ServeLight-3.4.4.dist-info/METADATA
ServeLight-3.4.4.dist-info/WHEEL
ServeLight-3.4.4.dist-info/top_level.txt
ServeLight-3.4.4.dist-info/zip-safe
ServeLight-3.4.4.dist-info/RECORD
