Metadata-Version: 2.1
Name: ServeLight
Version: 3.4.4
Summary: Lightweight and Responsive Server Framework
Home-page: https://github.com/Ksengine/ServeLight
Author: Kavindu Santhusa
Author-email: kavindusanthusa@gmail.com
License: MIT
Download-URL: https://pypi.python.org/pypi/ServeLight
Project-URL: Download, https://github.com/Ksengine/ServeLight/issues
Project-URL: Bug Tracker, https://github.com/Ksengine/ServeLight/issues
Keywords: simple,lightweight,WSGI,micro,server,library,python
Platform: any
Classifier: Intended Audience :: Developers
Classifier: Development Status :: 5 - Production/Stable
Classifier: Operating System :: OS Independent
Classifier: License :: OSI Approved :: MIT License
Classifier: Operating System :: MacOS :: MacOS X
Classifier: Operating System :: Microsoft :: Windows
Classifier: Operating System :: POSIX
Classifier: Programming Language :: Python
Classifier: Programming Language :: Python :: 2.7
Classifier: Programming Language :: Python :: 3.4
Classifier: Programming Language :: Python :: 3.5
Classifier: Programming Language :: Python :: 3.6
Classifier: Programming Language :: Python :: 3.7
Classifier: Programming Language :: Python :: 3
